jupyterlab_transformers_completer/__init__.py
jupyterlab_transformers_completer/_version.py
jupyterlab_transformers_completer-0.3.0.data/data/etc/jupyter/jupyter_server_config.d/jupyterlab_transformers_completer.json
jupyterlab_transformers_completer-0.3.0.data/data/share/jupyter/labextensions/@jupyterlab/transformers-completer/package.json
jupyterlab_transformers_completer-0.3.0.data/data/share/jupyter/labextensions/@jupyterlab/transformers-completer/static/213.e59dfc8de12e64063153.js
jupyterlab_transformers_completer-0.3.0.data/data/share/jupyter/labextensions/@jupyterlab/transformers-completer/static/468.cb1c62bdaf01b682273e.js
jupyterlab_transformers_completer-0.3.0.data/data/share/jupyter/labextensions/@jupyterlab/transformers-completer/static/488.593a8bdbb534307f9db2.js
jupyterlab_transformers_completer-0.3.0.data/data/share/jupyter/labextensions/@jupyterlab/transformers-completer/static/488.593a8bdbb534307f9db2.js.LICENSE.txt
jupyterlab_transformers_completer-0.3.0.data/data/share/jupyter/labextensions/@jupyterlab/transformers-completer/static/747.82e78a8edf88647d214c.js
jupyterlab_transformers_completer-0.3.0.data/data/share/jupyter/labextensions/@jupyterlab/transformers-completer/static/remoteEntry.c35f93a8e4c705cb30c5.js
jupyterlab_transformers_completer-0.3.0.data/data/share/jupyter/labextensions/@jupyterlab/transformers-completer/static/style.js
jupyterlab_transformers_completer-0.3.0.data/data/share/jupyter/labextensions/@jupyterlab/transformers-completer/static/third-party-licenses.json
jupyterlab_transformers_completer-0.3.0.data/data/share/jupyter/labextensions/@jupyterlab/transformers-completer/install.json
jupyterlab_transformers_completer-0.3.0.dist-info/METADATA
jupyterlab_transformers_completer-0.3.0.dist-info/WHEEL
jupyterlab_transformers_completer-0.3.0.dist-info/licenses/LICENSE
jupyterlab_transformers_completer-0.3.0.dist-info/RECORD
