Metadata-Version: 2.3
Name: jupyterlab-transformers-completer
Version: 0.3.0
Dynamic: Keywords
Summary: Inline completion provider using tranformers.js for JupyterLab.
Project-URL: Homepage, https://github.com/krassowski/jupyterlab-transformers-completer
Project-URL: Bug Tracker, https://github.com/krassowski/jupyterlab-transformers-completer/issues
Project-URL: Repository, https://github.com/krassowski/jupyterlab-transformers-completer.git
Author-email: Michał Krassowski <mkrassowski@quansight.com>
License: BSD 3-Clause License
License-File: LICENSE
Classifier: Framework :: Jupyter
Classifier: Framework :: Jupyter :: JupyterLab
Classifier: Framework :: Jupyter :: JupyterLab :: 4
Classifier: Framework :: Jupyter :: JupyterLab :: Extensions
Classifier: Framework :: Jupyter :: JupyterLab :: Extensions :: Prebuilt
Classifier: License :: OSI Approved :: BSD License
Classifier: Programming Language :: Python
Classifier: Programming Language :: Python :: 3
Classifier: Programming Language :: Python :: 3.8
Classifier: Programming Language :: Python :: 3.9
Classifier: Programming Language :: Python :: 3.10
Classifier: Programming Language :: Python :: 3.11
Requires-Python: >=3.8
Requires-Dist: jupyterlab-server>=2.25.2
Requires-Dist: jupyterlab<5,>=4.1.0
